{
  "session_id": "session_20250717_165512",
  "start_time": "2025-07-17T16:55:12.566592",
  "configuration": {
    "voice": "alloy",
    "input_mode": "voice_server_vad",
    "output_mode": "both",
    "temperature": 0.8,
    "instructions": "You are a helpful assistant. Be conversational and brief."
  },
  "interactions": [],
  "statistics": {
    "total_interactions": 0,
    "total_user_audio_ms": 0,
    "total_assistant_audio_ms": 0,
    "total_user_text_chars": 0,
    "total_assistant_text_chars": 0,
    "vad_events": 0,
    "errors": 1
  },
  "errors_log": [
    {
      "timestamp": "2025-07-17T16:55:22.602077",
      "message": "Connection failed: Connection failed: timed out during opening handshake",
      "interaction_id": null
    }
  ]
}