{
  "summary": {
    "audio_chunks_processed": 7,
    "audio_chunks_filtered": 24,
    "total_audio_mb": 0.14,
    "pipeline_switches": 0,
    "filter_rate": 0.77
  },
  "pipeline_metrics": {
    "basic": {
      "total_chunks": 0,
      "total_bytes": 0,
      "total_time_ms": 0.0,
      "avg_time_per_chunk": 0,
      "processors": {
        "AudioValidator": {
          "enabled": true,
          "priority": 0,
          "chunks": 0,
          "time_ms": 0.0,
          "avg_time": 0.0,
          "errors": 0
        }
      }
    },
    "voice": {
      "total_chunks": 31,
      "total_bytes": 148800,
      "total_time_ms": 14.871835708618164,
      "avg_time_per_chunk": 0.47973663576187625,
      "processors": {
        "AudioValidator": {
          "enabled": true,
          "priority": 0,
          "chunks": 31,
          "time_ms": 0.6227493286132812,
          "avg_time": 0.020088688019783266,
          "errors": 0
        },
        "NoiseReducer": {
          "enabled": true,
          "priority": 10,
          "chunks": 31,
          "time_ms": 5.959510803222656,
          "avg_time": 0.1922422839749244,
          "errors": 0
        },
        "VolumeNormalizer": {
          "enabled": true,
          "priority": 50,
          "chunks": 31,
          "time_ms": 2.5870800018310547,
          "avg_time": 0.08345419360745338,
          "errors": 0
        },
        "VADProcessor": {
          "enabled": true,
          "priority": 50,
          "chunks": 7,
          "time_ms": 0.7457733154296875,
          "avg_time": 0.10653904506138392,
          "errors": 0
        }
      }
    },
    "quality": {
      "total_chunks": 0,
      "total_bytes": 0,
      "total_time_ms": 0.0,
      "avg_time_per_chunk": 0,
      "processors": {
        "AudioValidator": {
          "enabled": true,
          "priority": 0,
          "chunks": 0,
          "time_ms": 0.0,
          "avg_time": 0.0,
          "errors": 0
        },
        "NoiseReducer": {
          "enabled": true,
          "priority": 10,
          "chunks": 0,
          "time_ms": 0.0,
          "avg_time": 0.0,
          "errors": 0
        },
        "EchoCanceller": {
          "enabled": true,
          "priority": 10,
          "chunks": 0,
          "time_ms": 0.0,
          "avg_time": 0.0,
          "errors": 0
        },
        "VolumeNormalizer": {
          "enabled": true,
          "priority": 50,
          "chunks": 0,
          "time_ms": 0.0,
          "avg_time": 0.0,
          "errors": 0
        },
        "VADProcessor": {
          "enabled": true,
          "priority": 50,
          "chunks": 0,
          "time_ms": 0.0,
          "avg_time": 0.0,
          "errors": 0
        }
      }
    },
    "realtime": {
      "total_chunks": 0,
      "total_bytes": 0,
      "total_time_ms": 0.0,
      "avg_time_per_chunk": 0,
      "processors": {
        "AudioValidator": {
          "enabled": true,
          "priority": 0,
          "chunks": 0,
          "time_ms": 0.0,
          "avg_time": 0.0,
          "errors": 0
        },
        "VolumeNormalizer": {
          "enabled": true,
          "priority": 50,
          "chunks": 0,
          "time_ms": 0.0,
          "avg_time": 0.0,
          "errors": 0
        }
      }
    }
  }
}